jaxhelper/__init__.py
jaxhelper-0.0.5.dist-info/METADATA
jaxhelper-0.0.5.dist-info/WHEEL
jaxhelper-0.0.5.dist-info/top_level.txt
jaxhelper-0.0.5.dist-info/RECORD
