Metadata-Version: 2.1
Name: jaxhelper
Version: 0.0.5
Summary: Basic tools and helpers for Jax
Home-page: https://github.com/clashluke/jaxhelper
Author: Lucas Nestler
Author-email: github.jaxhelper@nestler.sh
License: BSD
Platform: UNKNOWN
Classifier: Development Status :: 5 - Production/Stable
Classifier: License :: OSI Approved :: BSD License
Classifier: Programming Language :: Python
Classifier: Programming Language :: Python :: 3.7
Classifier: Programming Language :: Python :: 3.8
Classifier: Programming Language :: Python :: 3.9
Classifier: Topic :: Software Development :: Libraries
Classifier: Topic :: Software Development :: Libraries :: Python Modules
Classifier: Intended Audience :: Developers
Requires-Python: >=3.7
